gymnasium_env_for_SPaRC/__init__.py
gymnasium_env_for_SPaRC/gym_env_for_SPaRC.py
gymnasium_env_for_SPaRC/register_env.py
gymnasium_env_for_SPaRC/render/__init__.py
gymnasium_env_for_SPaRC/render/human_renderer.py
gymnasium_env_for_SPaRC/render/llm_renderer.py
gym_env_sparc-0.1.14.dist-info/METADATA
gym_env_sparc-0.1.14.dist-info/WHEEL
gym_env_sparc-0.1.14.dist-info/entry_points.txt
gym_env_sparc-0.1.14.dist-info/licenses/LICENCE
gym_env_sparc-0.1.14.dist-info/RECORD
